nwave/__init__.py
nwave/audio.py
nwave/base/__init__.py
nwave/base/base_effect.py
nwave/batch.py
nwave/common/__init__.py
nwave/common/iter.py
nwave/core.py
nwave/effects.py
nwave/interlocked/__init__.py
nwave/interlocked/writer.py
nwave/py.typed
nwave/task.py
nwave-0.1.2.dist-info/LICENSE
nwave-0.1.2.dist-info/WHEEL
nwave-0.1.2.dist-info/METADATA
nwave-0.1.2.dist-info/RECORD
