Metadata-Version: 2.1
Name: nwave
Version: 0.1.2
Summary: Multithread batch resampling and waveform transforms
Home-page: https://github.com/ionite34/nwave
License: MIT
Keywords: audio,resampling,wav,wave,sound
Author: ionite34
Author-email: dev@ionite.io
Requires-Python: >=3.7.2,<3.11
Classifier: Development Status :: 3 - Alpha
Classifier: License :: OSI Approved :: MIT License
Classifier: Programming Language :: Python :: 3
Classifier: Programming Language :: Python :: 3.10
Classifier: Programming Language :: Python :: 3.8
Classifier: Programming Language :: Python :: 3.9
Classifier: Topic :: Multimedia :: Sound/Audio
Classifier: Topic :: Multimedia :: Sound/Audio :: Analysis
Classifier: Topic :: Multimedia :: Sound/Audio :: Conversion
Classifier: Topic :: Utilities
Requires-Dist: SoundFile (>=0.10.3,<0.11.0)
Requires-Dist: librosa (>=0.9.2,<0.10.0)
Requires-Dist: numba (>=0.55.2,<0.57.0)
Requires-Dist: samplerate (>=0.1.0,<0.2.0)
Requires-Dist: soxr (>=0.3.0,<0.4.0)
Project-URL: Repository, https://github.com/ionite34/nwave
